register2d/__init__.py
register2d/process.py
register2d/rotate.py
register2d-0.0.3.dist-info/licenses/LICENSE
register2d-0.0.3.dist-info/METADATA
register2d-0.0.3.dist-info/WHEEL
register2d-0.0.3.dist-info/top_level.txt
register2d-0.0.3.dist-info/RECORD
