Metadata-Version: 2.4
Name: register2d
Version: 0.0.3
Summary: A 2d black-white binary image registration algorithm.
Author-email: GGN_2015 <neko@jlulug.org>
License: MIT License
Requires-Python: >=3.10
License-File: LICENSE
Requires-Dist: cupy
Requires-Dist: numpy
Requires-Dist: tqdm
Requires-Dist: pillow
Requires-Dist: cupy_fft_match
Requires-Dist: rawtimer
Dynamic: license-file
